{
	"info": {
		"_postman_id": "3b940466-3a16-4ecb-9aba-82f3ced97071",
		"name": "PostmanCollection_Seminar8",
		"schema": "https://schema.getpostman.com/json/collection/v2.1.0/collection.json"
	},
	"item": [
		{
			"name": "http://localhost:8088/users/get/user1",
			"request": {
				"method": "GET",
				"header": [],
				"url": {
					"raw": "http://localhost:8088/users/get/user1",
					"protocol": "http",
					"host": [
						"localhost"
					],
					"port": "8088",
					"path": [
						"users",
						"get",
						"user1"
					]
				}
			},
			"response": []
		},
		{
			"name": "http://localhost:8088/users/addUsers",
			"request": {
				"method": "POST",
				"header": [],
				"body": {
					"mode": "raw",
					"raw": "{\r\n    \"username\" : \"test1\",\r\n    \"fullName\" : \"Alexandru Ion\",\r\n    \"cnp\": \"89481147\",\r\n    \"age\" : 27,\r\n    \"userType\" : \"STUDENT\",\r\n    \"otherInformation\" : \"no more info\"\r\n}",
					"options": {
						"raw": {
							"language": "json"
						}
					}
				},
				"url": {
					"raw": "http://localhost:8088/users/addUsers",
					"protocol": "http",
					"host": [
						"localhost"
					],
					"port": "8088",
					"path": [
						"users",
						"addUsers"
					]
				}
			},
			"response": []
		},
		{
			"name": "http://localhost:8088/users/getAll",
			"request": {
				"method": "GET",
				"header": [],
				"url": {
					"raw": "http://localhost:8088/users/getAll",
					"protocol": "http",
					"host": [
						"localhost"
					],
					"port": "8088",
					"path": [
						"users",
						"getAll"
					]
				}
			},
			"response": []
		}
	]
}